cpr/__init__.py
cpr/cones.py
cpr/cvxpy_interface.py
cpr/lsqr.py
cpr/problem.py
cpr/refine.py
cpr/solvers.py
cpr/sparse_matvec.py
cpr/utils.py
cpsr/__init__.py
cpsr/cones.py
cpsr/cvxpy_interface.py
cpsr/lsqr.py
cpsr/problem.py
cpsr/refine.py
cpsr/solvers.py
cpsr/sparse_matvec.py
cpsr/utils.py
cpr-0.1.dist-info/LICENSE
cpr-0.1.dist-info/METADATA
cpr-0.1.dist-info/WHEEL
cpr-0.1.dist-info/top_level.txt
cpr-0.1.dist-info/RECORD
